oakx_grape/__init__.py
oakx_grape/grape_implementation.py
oakx_grape/loader.py
oakx_grape/test.js
oakx_grape-0.1.2.dist-info/entry_points.txt
oakx_grape-0.1.2.dist-info/LICENSE
oakx_grape-0.1.2.dist-info/WHEEL
oakx_grape-0.1.2.dist-info/METADATA
oakx_grape-0.1.2.dist-info/RECORD
