Metadata-Version: 2.1
Name: oakx-grape
Version: 0.1.2
Summary: oakx-grape
License: BSD 3
Author: Harshad Hegde
Author-email: hhegde@lbl.gov
Requires-Python: >=3.9,<3.12
Classifier: License :: Other/Proprietary License
Classifier: Programming Language :: Python :: 3
Classifier: Programming Language :: Python :: 3.9
Classifier: Programming Language :: Python :: 3.10
Classifier: Programming Language :: Python :: 3.11
Provides-Extra: docs
Requires-Dist: bioregistry (>=0.5.136,<0.6.0)
Requires-Dist: click (>=8.1.3,<9.0.0)
Requires-Dist: ensmallen (==0.8.28)
Requires-Dist: furo[docs] (>=2022.9.29,<2023.0.0); extra == "docs"
Requires-Dist: grape
Requires-Dist: importlib (>=1.0.4,<2.0.0)
Requires-Dist: myst-parser[docs] (>=0.18.1,<0.19.0); extra == "docs"
Requires-Dist: oaklib (>=0.1.43,<0.2.0)
Requires-Dist: scipy (>=1.9.0,<2.0.0)
Requires-Dist: sphinx-autodoc-typehints[docs] (>=1.19.4,<2.0.0); extra == "docs"
Requires-Dist: sphinx-click[docs] (>=4.3.0,<5.0.0); extra == "docs"
Requires-Dist: sphinx[docs] (>=5.3.0,<6.0.0); extra == "docs"
Requires-Dist: tox (>=3.25.1,<4.0.0)
